{
  "title": "Preferences",
  "description": "Das Objekt beschreibt die Präferenzen gegenüber Mitfahrern.",
  "type": "object",
  "required": [
    "id",
    "type"
  ],
  "properties": {
    "id": {
      "type": "string",
      "format": "url"
    },
    "type": {
      "type": "string",
      "pattern": "^https\\:\\/\\/schema\\.mmport\\.org\\/1\\.0\\/Preferences$"
    },
    "created": {
      "description": "Zeitpunkt der Erstellung.",
      "type": "string",
      "format": "date-time"
    },
    "modified": {
      "description": "Zeitpunkt der letzten Änderung.",
      "type": "string",
      "format": "date-time"
    },
    "person": {
      "description": "Person, dem die Einstellungen gehören",
      "references": "Person",
      "backreference": "person",
      "cardinality": "1:1",
      "type": "string",
      "format": "url"
    },
    "nonsmoking": {
      "description": "Nichtraucher-Fahrt.",
      "type": "boolean"
    },
    "gender": {
      "description": "Gender der MitfahrerInnen. Es SOLLTEN die Begriffe female fü weiblich und male für männlich verwendet werden. Andere Geschlechter SOLLTEN klein geschrieben und in englisch beschrieben werden.",
      "type": "string"
    },
    "bike": {
      "description": "Fahrradmitnahme erwünscht"
    },
    "ageFrom": {
      "description": "Mindestalter der MitfahrerInnen, numerischer Wert.",
      "type": "integer"
    },
    "ageTo": {
      "description": "Maximales Alter der MitfahrerInnen, numerischer Wert.",
      "type": "integer"
    },
    "talkingLevel": {
      "description": "Das Level an Gesprächigkeit.",
      "type": "float",
      "minimum": 0,
      "maximum": 1
    }
  }
}